optimizador_joshua/__init__.py
optimizador_joshua/funciones/__init__.py
optimizador_joshua/funciones/base.py
optimizador_joshua/funciones/objective.py
optimizador_joshua/funciones/restrictive.py
optimizador_joshua/funciones/univariablef.py
optimizador_joshua/optimizador/__init__.py
optimizador_joshua/optimizador/base.py
optimizador_joshua/optimizador/multivariable.py
optimizador_joshua/optimizador/univariable.py
optimizador_joshua/optimizador/byregions/__init__.py
optimizador_joshua/optimizador/byregions/byregions.py
optimizador_joshua/optimizador/byregions/fibonacci.py
optimizador_joshua/optimizador/byregions/golden.py
optimizador_joshua/optimizador/byregions/interval.py
optimizador_joshua/optimizador/derivate/__init__.py
optimizador_joshua/optimizador/derivate/biseccion.py
optimizador_joshua/optimizador/derivate/derivate.py
optimizador_joshua/optimizador/derivate/newtonraphson.py
optimizador_joshua/optimizador/derivate/secante.py
optimizador_joshua/optimizador/direct/__init__.py
optimizador_joshua/optimizador/direct/directmethods.py
optimizador_joshua/optimizador/direct/hookejeeves.py
optimizador_joshua/optimizador/direct/neldermead.py
optimizador_joshua/optimizador/direct/randomwalk.py
optimizador_joshua/optimizador/gradient/__init__.py
optimizador_joshua/optimizador/gradient/cauchy.py
optimizador_joshua/optimizador/gradient/fletcherreeves.py
optimizador_joshua/optimizador/gradient/gradientmethods.py
optimizador_joshua/optimizador/gradient/newtonmethod.py
optimizador_joshua-0.3.2.dist-info/METADATA
optimizador_joshua-0.3.2.dist-info/WHEEL
optimizador_joshua-0.3.2.dist-info/top_level.txt
optimizador_joshua-0.3.2.dist-info/RECORD
